dune/translate/__init__.py
dune/translate/constants.py
dune/translate/custom_transforms.py
dune/translate/errors.py
dune/translate/table_replacements.py
dune/translate/translate.py
dune_query_translator-0.6.0.dist-info/LICENSE
dune_query_translator-0.6.0.dist-info/METADATA
dune_query_translator-0.6.0.dist-info/WHEEL
dune_query_translator-0.6.0.dist-info/RECORD
