Metadata-Version: 2.1
Name: dune-query-translator
Version: 0.6.0
Summary: 
Author: Vegard Stikbakke
Author-email: vegard@dune.com
Requires-Python: >=3.11,<4.0
Classifier: Programming Language :: Python :: 3
Classifier: Programming Language :: Python :: 3.11
Requires-Dist: sqlglot (>=11.4.4,<12.0.0)
